MANIFEST.in
README.txt
setup.cfg
setup.py
docs/HISTORY.txt
docs/INSTALL.txt
docs/LICENSE.GPL
docs/LICENSE.txt
ityou/__init__.py
ityou.workflow.egg-info/PKG-INFO
ityou.workflow.egg-info/SOURCES.txt
ityou.workflow.egg-info/dependency_links.txt
ityou.workflow.egg-info/entry_points.txt
ityou.workflow.egg-info/namespace_packages.txt
ityou.workflow.egg-info/not-zip-safe
ityou.workflow.egg-info/paster_plugins.txt
ityou.workflow.egg-info/requires.txt
ityou.workflow.egg-info/top_level.txt
ityou/workflow/__init__.py
ityou/workflow/configure.zcml
ityou/workflow/interfaces.py
ityou/workflow/tests.py
ityou/workflow/translate.sh
ityou/workflow/Extensions/Install.py
ityou/workflow/Extensions/__init__.py
ityou/workflow/browser/__init__.py
ityou/workflow/browser/configure.zcml
ityou/workflow/browser/controlpanel.py
ityou/workflow/browser/todo.py
ityou/workflow/browser/images/README.txt
ityou/workflow/browser/images/Sorting icons.psd
ityou/workflow/browser/images/back_disabled.jpg
ityou/workflow/browser/images/back_disabled.png
ityou/workflow/browser/images/back_enabled.jpg
ityou/workflow/browser/images/back_enabled.png
ityou/workflow/browser/images/forward_disabled.jpg
ityou/workflow/browser/images/forward_disabled.png
ityou/workflow/browser/images/forward_enabled.jpg
ityou/workflow/browser/images/forward_enabled.png
ityou/workflow/browser/images/ityou-esi-workflow-icon.png
ityou/workflow/browser/images/sort_asc.png
ityou/workflow/browser/images/sort_asc_disabled.png
ityou/workflow/browser/images/sort_both.png
ityou/workflow/browser/images/sort_desc.png
ityou/workflow/browser/images/sort_desc_disabled.png
ityou/workflow/browser/javascripts/dataTables.german.txt
ityou/workflow/browser/javascripts/jquery.dataTables.js
ityou/workflow/browser/javascripts/jquery.tmpl.min.js
ityou/workflow/browser/javascripts/todo-jq.js
ityou/workflow/browser/stylesheets/todo-table.css
ityou/workflow/browser/stylesheets/todo.css
ityou/workflow/browser/templates/todo.pt
ityou/workflow/locales/ityou.workflow.pot
ityou/workflow/locales/de/LC_MESSAGES/ityou.workflow.po
ityou/workflow/locales/en/LC_MESSAGES/ityou.workflow.po
ityou/workflow/profiles/default/browserlayer.xml
ityou/workflow/profiles/default/controlpanel.xml
ityou/workflow/profiles/default/cssregistry.xml
ityou/workflow/profiles/default/jsregistry.xml
ityou/workflow/profiles/default/metadata.xml
